cookesgot/__init__.py
cookesgot/main.py
fmfocus/__init__.py
fmfocus/main.py
cookesgot-0.1.0.dist-info/METADATA
cookesgot-0.1.0.dist-info/WHEEL
cookesgot-0.1.0.dist-info/top_level.txt
cookesgot-0.1.0.dist-info/RECORD
