Metadata-Version: 2.1
Name: cookesgot
Version: 0.1.0
Summary: UNKNOWN
Home-page: UNKNOWN
Author: Your Name
Author-email: UNKNOWN
License: UNKNOWN
Platform: UNKNOWN
Requires-Dist: requests
Requires-Dist: pyautogui
Requires-Dist: selenium
